{
    "square1": {
        "origin": [
            -22.5,
            -22.5
        ],
        "size": 15.0,
        "spacing": 2.4
    },
    "square2": {
        "origin": [
            -7.5,
            -22.5
        ],
        "size": 15.0,
        "spacing": 2.4
    },
    "square3": {
        "origin": [
            7.5,
            -22.5
        ],
        "size": 15.0,
        "spacing": 2.4
    },
    "square4": {
        "origin": [
            22.5,
            -22.5
        ],
        "size": 15.0,
        "spacing": 2.4
    },
    "square5": {
        "origin": [
            -22.5,
            -7.5
        ],
        "size": 15.0,
        "spacing": 2.4
    },
    "square6": {
        "origin": [
            22.5,
            -7.5
        ],
        "size": 15.0,
        "spacing": 2.4
    },
    "square7": {
        "origin": [
            -22.5,
            7.5
        ],
        "size": 15.0,
        "spacing": 2.4
    },
    "square8": {
        "origin": [
            22.5,
            7.5
        ],
        "size": 15.0,
        "spacing": 2.4
    },
    "square9": {
        "origin": [
            -22.5,
            22.5
        ],
        "size": 15.0,
        "spacing": 2.4
    },
    "square10": {
        "origin": [
            -7.5,
            22.5
        ],
        "size": 15.0,
        "spacing": 2.4
    },
    "square11": {
        "origin": [
            7.5,
            22.5
        ],
        "size": 15.0,
        "spacing": 2.4
    },
    "square12": {
        "origin": [
            22.5,
            22.5
        ],
        "size": 15.0,
        "spacing": 2.4
    },
    "square13": {
        "origin": [
            -11.25,
            -11.25
        ],
        "size": 7.5,
        "spacing": 1.2
    },
    "square14": {
        "origin": [
            -3.75,
            -11.25
        ],
        "size": 7.5,
        "spacing": 1.2
    },
    "square15": {
        "origin": [
            3.75,
            -11.25
        ],
        "size": 7.5,
        "spacing": 1.2
    },
    "square16": {
        "origin": [
            11.25,
            -11.25
        ],
        "size": 7.5,
        "spacing": 1.2
    },
    "square17": {
        "origin": [
            -11.25,
            -3.75
        ],
        "size": 7.5,
        "spacing": 1.2
    },
    "square18": {
        "origin": [
            11.25,
            -3.75
        ],
        "size": 7.5,
        "spacing": 1.2
    },
    "square19": {
        "origin": [
            -11.25,
            3.75
        ],
        "size": 7.5,
        "spacing": 1.2
    },
    "square20": {
        "origin": [
            11.25,
            3.75
        ],
        "size": 7.5,
        "spacing": 1.2
    },
    "square21": {
        "origin": [
            -11.25,
            11.25
        ],
        "size": 7.5,
        "spacing": 1.2
    },
    "square22": {
        "origin": [
            -3.75,
            11.25
        ],
        "size": 7.5,
        "spacing": 1.2
    },
    "square23": {
        "origin": [
            3.75,
            11.25
        ],
        "size": 7.5,
        "spacing": 1.2
    },
    "square24": {
        "origin": [
            11.25,
            11.25
        ],
        "size": 7.5,
        "spacing": 1.2
    },
    "square25": {
        "origin": [
            -5.625,
            -5.625
        ],
        "size": 3.75,
        "spacing": 0.6
    },
    "square26": {
        "origin": [
            -1.875,
            -5.625
        ],
        "size": 3.75,
        "spacing": 0.6
    },
    "square27": {
        "origin": [
            1.875,
            -5.625
        ],
        "size": 3.75,
        "spacing": 0.6
    },
    "square28": {
        "origin": [
            5.625,
            -5.625
        ],
        "size": 3.75,
        "spacing": 0.6
    },
    "square29": {
        "origin": [
            -5.625,
            -1.875
        ],
        "size": 3.75,
        "spacing": 0.6
    },
    "square30": {
        "origin": [
            5.625,
            -1.875
        ],
        "size": 3.75,
        "spacing": 0.6
    },
    "square31": {
        "origin": [
            -5.625,
            1.875
        ],
        "size": 3.75,
        "spacing": 0.6
    },
    "square32": {
        "origin": [
            5.625,
            1.875
        ],
        "size": 3.75,
        "spacing": 0.6
    },
    "square33": {
        "origin": [
            -5.625,
            5.625
        ],
        "size": 3.75,
        "spacing": 0.6
    },
    "square34": {
        "origin": [
            -1.875,
            5.625
        ],
        "size": 3.75,
        "spacing": 0.6
    },
    "square35": {
        "origin": [
            1.875,
            5.625
        ],
        "size": 3.75,
        "spacing": 0.6
    },
    "square36": {
        "origin": [
            5.625,
            5.625
        ],
        "size": 3.75,
        "spacing": 0.6
    },
    "square37": {
        "origin": [
            -1.875,
            -1.875
        ],
        "size": 3.75,
        "spacing": 0.6
    },
    "square38": {
        "origin": [
            1.875,
            -1.875
        ],
        "size": 3.75,
        "spacing": 0.6
    },
    "square39": {
        "origin": [
            -1.875,
            1.875
        ],
        "size": 3.75,
        "spacing": 0.6
    },
    "square40": {
        "origin": [
            1.875,
            1.875
        ],
        "size": 3.75,
        "spacing": 0.6
    }
}